[{"condition_qty":5.000,"product_id":14,"updated_by":125,"promotion_scheme_id":108,"promotion_id":65,"created_date":"2021-12-14 17:32:07.004","updated_date":"2021-12-14 17:32:07.004","created_by":125,"version":1,"promotion_condition_id":327},{"condition_qty":5.000,"product_id":15,"updated_by":125,"promotion_scheme_id":108,"promotion_id":65,"created_date":"2021-12-14 17:32:07.004","updated_date":"2021-12-14 17:32:07.004","created_by":125,"version":1,"promotion_condition_id":328},{"condition_qty":5.000,"product_id":10,"updated_by":125,"promotion_scheme_id":109,"promotion_id":65,"created_date":"2021-12-14 17:32:07.019","updated_date":"2021-12-14 17:32:07.019","created_by":125,"version":1,"promotion_condition_id":329},{"condition_qty":5.000,"product_id":11,"updated_by":125,"promotion_scheme_id":109,"promotion_id":65,"created_date":"2021-12-14 17:32:07.019","updated_date":"2021-12-14 17:32:07.019","created_by":125,"version":1,"promotion_condition_id":330},{"condition_qty":5.000,"product_id":12,"updated_by":125,"promotion_scheme_id":109,"promotion_id":65,"created_date":"2021-12-14 17:32:07.035","updated_date":"2021-12-14 17:32:07.035","created_by":125,"version":1,"promotion_condition_id":331},{"condition_qty":5.000,"product_id":13,"updated_by":125,"promotion_scheme_id":109,"promotion_id":65,"created_date":"2021-12-14 17:32:07.035","updated_date":"2021-12-14 17:32:07.035","created_by":125,"version":1,"promotion_condition_id":332},{"condition_qty":10.000,"product_id":14,"updated_by":125,"promotion_scheme_id":110,"promotion_id":66,"created_date":"2021-12-14 17:34:50.645","updated_date":"2021-12-14 17:34:50.645","created_by":125,"version":1,"promotion_condition_id":333},{"condition_qty":10.000,"product_id":15,"updated_by":125,"promotion_scheme_id":110,"promotion_id":66,"created_date":"2021-12-14 17:34:50.645","updated_date":"2021-12-14 17:34:50.645","created_by":125,"version":1,"promotion_condition_id":334},{"condition_qty":10.000,"product_id":10,"updated_by":125,"promotion_scheme_id":111,"promotion_id":66,"created_date":"2021-12-14 17:34:50.660","updated_date":"2021-12-14 17:34:50.660","created_by":125,"version":1,"promotion_condition_id":335},{"condition_qty":10.000,"product_id":11,"updated_by":125,"promotion_scheme_id":111,"promotion_id":66,"created_date":"2021-12-14 17:34:50.676","updated_date":"2021-12-14 17:34:50.676","created_by":125,"version":1,"promotion_condition_id":336},{"condition_qty":10.000,"product_id":12,"updated_by":125,"promotion_scheme_id":111,"promotion_id":66,"created_date":"2021-12-14 17:34:50.676","updated_date":"2021-12-14 17:34:50.676","created_by":125,"version":1,"promotion_condition_id":337},{"condition_qty":10.000,"product_id":13,"updated_by":125,"promotion_scheme_id":111,"promotion_id":66,"created_date":"2021-12-14 17:34:50.676","updated_date":"2021-12-14 17:34:50.676","created_by":125,"version":1,"promotion_condition_id":338},{"condition_qty":7.000,"product_id":14,"updated_by":125,"promotion_scheme_id":112,"promotion_id":67,"created_date":"2021-12-14 17:36:14.724","updated_date":"2021-12-14 17:36:14.724","created_by":125,"version":1,"promotion_condition_id":339},{"condition_qty":7.000,"product_id":15,"updated_by":125,"promotion_scheme_id":112,"promotion_id":67,"created_date":"2021-12-14 17:36:14.739","updated_date":"2021-12-14 17:36:14.739","created_by":125,"version":1,"promotion_condition_id":340},{"condition_qty":5.000,"product_id":10,"updated_by":125,"promotion_scheme_id":113,"promotion_id":67,"created_date":"2021-12-14 17:36:14.739","updated_date":"2021-12-14 17:36:14.739","created_by":125,"version":1,"promotion_condition_id":341},{"condition_qty":5.000,"product_id":11,"updated_by":125,"promotion_scheme_id":113,"promotion_id":67,"created_date":"2021-12-14 17:36:14.739","updated_date":"2021-12-14 17:36:14.739","created_by":125,"version":1,"promotion_condition_id":342},{"condition_qty":5.000,"product_id":12,"updated_by":125,"promotion_scheme_id":113,"promotion_id":67,"created_date":"2021-12-14 17:36:14.755","updated_date":"2021-12-14 17:36:14.755","created_by":125,"version":1,"promotion_condition_id":343},{"condition_qty":5.000,"product_id":13,"updated_by":125,"promotion_scheme_id":113,"promotion_id":67,"created_date":"2021-12-14 17:36:14.755","updated_date":"2021-12-14 17:36:14.755","created_by":125,"version":1,"promotion_condition_id":344},{"condition_qty":5.000,"product_id":14,"updated_by":125,"promotion_scheme_id":114,"promotion_id":68,"created_date":"2021-12-14 17:38:23.069","updated_date":"2021-12-14 17:38:23.069","created_by":125,"version":1,"promotion_condition_id":345},{"condition_qty":5.000,"product_id":15,"updated_by":125,"promotion_scheme_id":114,"promotion_id":68,"created_date":"2021-12-14 17:38:23.069","updated_date":"2021-12-14 17:38:23.069","created_by":125,"version":1,"promotion_condition_id":346},{"condition_qty":5.000,"product_id":10,"updated_by":125,"promotion_scheme_id":115,"promotion_id":68,"created_date":"2021-12-14 17:38:23.084","updated_date":"2021-12-14 17:38:23.084","created_by":125,"version":1,"promotion_condition_id":347},{"condition_qty":5.000,"product_id":11,"updated_by":125,"promotion_scheme_id":115,"promotion_id":68,"created_date":"2021-12-14 17:38:23.084","updated_date":"2021-12-14 17:38:23.084","created_by":125,"version":1,"promotion_condition_id":348},{"condition_qty":5.000,"product_id":12,"updated_by":125,"promotion_scheme_id":115,"promotion_id":68,"created_date":"2021-12-14 17:38:23.084","updated_date":"2021-12-14 17:38:23.084","created_by":125,"version":1,"promotion_condition_id":349},{"condition_qty":5.000,"product_id":13,"updated_by":125,"promotion_scheme_id":115,"promotion_id":68,"created_date":"2021-12-14 17:38:23.084","updated_date":"2021-12-14 17:38:23.084","created_by":125,"version":1,"promotion_condition_id":350},{"condition_qty":1.000,"product_id":14,"updated_by":125,"promotion_scheme_id":116,"promotion_id":69,"created_date":"2021-12-14 17:39:52.959","updated_date":"2021-12-14 17:39:52.959","created_by":125,"version":1,"promotion_condition_id":351},{"condition_qty":1.000,"product_id":15,"updated_by":125,"promotion_scheme_id":116,"promotion_id":69,"created_date":"2021-12-14 17:39:52.959","updated_date":"2021-12-14 17:39:52.959","created_by":125,"version":1,"promotion_condition_id":352},{"condition_qty":1.000,"product_id":10,"updated_by":125,"promotion_scheme_id":117,"promotion_id":69,"created_date":"2021-12-14 17:39:52.975","updated_date":"2021-12-14 17:39:52.975","created_by":125,"version":1,"promotion_condition_id":353},{"condition_qty":1.000,"product_id":11,"updated_by":125,"promotion_scheme_id":117,"promotion_id":69,"created_date":"2021-12-14 17:39:52.975","updated_date":"2021-12-14 17:39:52.975","created_by":125,"version":1,"promotion_condition_id":354},{"condition_qty":1.000,"product_id":12,"updated_by":125,"promotion_scheme_id":117,"promotion_id":69,"created_date":"2021-12-14 17:39:52.975","updated_date":"2021-12-14 17:39:52.975","created_by":125,"version":1,"promotion_condition_id":355},{"condition_qty":1.000,"product_id":13,"updated_by":125,"promotion_scheme_id":117,"promotion_id":69,"created_date":"2021-12-14 17:39:52.975","updated_date":"2021-12-14 17:39:52.975","created_by":125,"version":1,"promotion_condition_id":356},{"condition_qty":3.000,"product_id":14,"updated_by":125,"promotion_scheme_id":118,"promotion_id":70,"created_date":"2021-12-14 17:41:05.084","updated_date":"2021-12-14 17:41:05.084","created_by":125,"version":1,"promotion_condition_id":357},{"condition_qty":3.000,"product_id":15,"updated_by":125,"promotion_scheme_id":118,"promotion_id":70,"created_date":"2021-12-14 17:41:05.084","updated_date":"2021-12-14 17:41:05.084","created_by":125,"version":1,"promotion_condition_id":358},{"condition_qty":2.000,"product_id":10,"updated_by":125,"promotion_scheme_id":119,"promotion_id":70,"created_date":"2021-12-14 17:41:05.100","updated_date":"2021-12-14 17:41:05.100","created_by":125,"version":1,"promotion_condition_id":359},{"condition_qty":2.000,"product_id":11,"updated_by":125,"promotion_scheme_id":119,"promotion_id":70,"created_date":"2021-12-14 17:41:05.100","updated_date":"2021-12-14 17:41:05.100","created_by":125,"version":1,"promotion_condition_id":360},{"condition_qty":2.000,"product_id":12,"updated_by":125,"promotion_scheme_id":119,"promotion_id":70,"created_date":"2021-12-14 17:41:05.100","updated_date":"2021-12-14 17:41:05.100","created_by":125,"version":1,"promotion_condition_id":361},{"condition_qty":2.000,"product_id":13,"updated_by":125,"promotion_scheme_id":119,"promotion_id":70,"created_date":"2021-12-14 17:41:05.100","updated_date":"2021-12-14 17:41:05.100","created_by":125,"version":1,"promotion_condition_id":362},{"condition_qty":3.000,"product_id":14,"updated_by":125,"promotion_scheme_id":120,"promotion_id":71,"created_date":"2021-12-14 17:42:15.241","updated_date":"2021-12-14 17:42:15.241","created_by":125,"version":1,"promotion_condition_id":363},{"condition_qty":3.000,"product_id":15,"updated_by":125,"promotion_scheme_id":120,"promotion_id":71,"created_date":"2021-12-14 17:42:15.241","updated_date":"2021-12-14 17:42:15.241","created_by":125,"version":1,"promotion_condition_id":364},{"condition_qty":2.000,"product_id":10,"updated_by":125,"promotion_scheme_id":121,"promotion_id":71,"created_date":"2021-12-14 17:42:15.256","updated_date":"2021-12-14 17:42:15.256","created_by":125,"version":1,"promotion_condition_id":365},{"condition_qty":2.000,"product_id":11,"updated_by":125,"promotion_scheme_id":121,"promotion_id":71,"created_date":"2021-12-14 17:42:15.256","updated_date":"2021-12-14 17:42:15.256","created_by":125,"version":1,"promotion_condition_id":366},{"condition_qty":2.000,"product_id":12,"updated_by":125,"promotion_scheme_id":121,"promotion_id":71,"created_date":"2021-12-14 17:42:15.256","updated_date":"2021-12-14 17:42:15.256","created_by":125,"version":1,"promotion_condition_id":367},{"condition_qty":2.000,"product_id":13,"updated_by":125,"promotion_scheme_id":121,"promotion_id":71,"created_date":"2021-12-14 17:42:15.272","updated_date":"2021-12-14 17:42:15.272","created_by":125,"version":1,"promotion_condition_id":368},{"condition_qty":15.000,"product_id":14,"updated_by":125,"promotion_scheme_id":122,"promotion_id":72,"created_date":"2021-12-14 17:43:22.100","updated_date":"2021-12-14 17:43:22.100","created_by":125,"version":1,"promotion_condition_id":369},{"condition_qty":15.000,"product_id":15,"updated_by":125,"promotion_scheme_id":122,"promotion_id":72,"created_date":"2021-12-14 17:43:22.100","updated_date":"2021-12-14 17:43:22.100","created_by":125,"version":1,"promotion_condition_id":370},{"condition_qty":10.000,"product_id":10,"updated_by":125,"promotion_scheme_id":123,"promotion_id":72,"created_date":"2021-12-14 17:43:22.132","updated_date":"2021-12-14 17:43:22.132","created_by":125,"version":1,"promotion_condition_id":371},{"condition_qty":10.000,"product_id":11,"updated_by":125,"promotion_scheme_id":123,"promotion_id":72,"created_date":"2021-12-14 17:43:22.132","updated_date":"2021-12-14 17:43:22.132","created_by":125,"version":1,"promotion_condition_id":372},{"condition_qty":10.000,"product_id":12,"updated_by":125,"promotion_scheme_id":123,"promotion_id":72,"created_date":"2021-12-14 17:43:22.147","updated_date":"2021-12-14 17:43:22.147","created_by":125,"version":1,"promotion_condition_id":373},{"condition_qty":10.000,"product_id":13,"updated_by":125,"promotion_scheme_id":123,"promotion_id":72,"created_date":"2021-12-14 17:43:22.147","updated_date":"2021-12-14 17:43:22.147","created_by":125,"version":1,"promotion_condition_id":374},{"condition_qty":7.000,"product_id":14,"updated_by":125,"promotion_scheme_id":124,"promotion_id":73,"created_date":"2021-12-14 17:46:49.337","updated_date":"2021-12-14 17:46:49.337","created_by":125,"version":1,"promotion_condition_id":375},{"condition_qty":7.000,"product_id":15,"updated_by":125,"promotion_scheme_id":124,"promotion_id":73,"created_date":"2021-12-14 17:46:49.352","updated_date":"2021-12-14 17:46:49.352","created_by":125,"version":1,"promotion_condition_id":376},{"condition_qty":5.000,"product_id":10,"updated_by":125,"promotion_scheme_id":125,"promotion_id":73,"created_date":"2021-12-14 17:46:49.352","updated_date":"2021-12-14 17:46:49.352","created_by":125,"version":1,"promotion_condition_id":377},{"condition_qty":5.000,"product_id":11,"updated_by":125,"promotion_scheme_id":125,"promotion_id":73,"created_date":"2021-12-14 17:46:49.368","updated_date":"2021-12-14 17:46:49.368","created_by":125,"version":1,"promotion_condition_id":378},{"condition_qty":5.000,"product_id":12,"updated_by":125,"promotion_scheme_id":125,"promotion_id":73,"created_date":"2021-12-14 17:46:49.368","updated_date":"2021-12-14 17:46:49.368","created_by":125,"version":1,"promotion_condition_id":379},{"condition_qty":5.000,"product_id":13,"updated_by":125,"promotion_scheme_id":125,"promotion_id":73,"created_date":"2021-12-14 17:46:49.368","updated_date":"2021-12-14 17:46:49.368","created_by":125,"version":1,"promotion_condition_id":380},{"condition_qty":3.000,"product_id":14,"updated_by":125,"promotion_scheme_id":126,"promotion_id":74,"created_date":"2021-12-14 17:47:43.727","updated_date":"2021-12-14 17:47:43.727","created_by":125,"version":1,"promotion_condition_id":381},{"condition_qty":3.000,"product_id":15,"updated_by":125,"promotion_scheme_id":126,"promotion_id":74,"created_date":"2021-12-14 17:47:43.727","updated_date":"2021-12-14 17:47:43.727","created_by":125,"version":1,"promotion_condition_id":382},{"condition_qty":2.000,"product_id":10,"updated_by":125,"promotion_scheme_id":127,"promotion_id":74,"created_date":"2021-12-14 17:47:43.743","updated_date":"2021-12-14 17:47:43.743","created_by":125,"version":1,"promotion_condition_id":383},{"condition_qty":2.000,"product_id":11,"updated_by":125,"promotion_scheme_id":127,"promotion_id":74,"created_date":"2021-12-14 17:47:43.743","updated_date":"2021-12-14 17:47:43.743","created_by":125,"version":1,"promotion_condition_id":384},{"condition_qty":2.000,"product_id":12,"updated_by":125,"promotion_scheme_id":127,"promotion_id":74,"created_date":"2021-12-14 17:47:43.743","updated_date":"2021-12-14 17:47:43.743","created_by":125,"version":1,"promotion_condition_id":385},{"condition_qty":2.000,"product_id":13,"updated_by":125,"promotion_scheme_id":127,"promotion_id":74,"created_date":"2021-12-14 17:47:43.759","updated_date":"2021-12-14 17:47:43.759","created_by":125,"version":1,"promotion_condition_id":386},{"condition_qty":5.000,"product_id":14,"updated_by":125,"promotion_scheme_id":128,"promotion_id":75,"created_date":"2021-12-14 17:48:27.963","updated_date":"2021-12-14 17:48:27.963","created_by":125,"version":1,"promotion_condition_id":387},{"condition_qty":5.000,"product_id":15,"updated_by":125,"promotion_scheme_id":128,"promotion_id":75,"created_date":"2021-12-14 17:48:27.963","updated_date":"2021-12-14 17:48:27.963","created_by":125,"version":1,"promotion_condition_id":388},{"condition_qty":5.000,"product_id":10,"updated_by":125,"promotion_scheme_id":129,"promotion_id":75,"created_date":"2021-12-14 17:48:27.978","updated_date":"2021-12-14 17:48:27.978","created_by":125,"version":1,"promotion_condition_id":389},{"condition_qty":5.000,"product_id":11,"updated_by":125,"promotion_scheme_id":129,"promotion_id":75,"created_date":"2021-12-14 17:48:27.978","updated_date":"2021-12-14 17:48:27.978","created_by":125,"version":1,"promotion_condition_id":390},{"condition_qty":5.000,"product_id":12,"updated_by":125,"promotion_scheme_id":129,"promotion_id":75,"created_date":"2021-12-14 17:48:27.978","updated_date":"2021-12-14 17:48:27.978","created_by":125,"version":1,"promotion_condition_id":391},{"condition_qty":5.000,"product_id":13,"updated_by":125,"promotion_scheme_id":129,"promotion_id":75,"created_date":"2021-12-14 17:48:27.978","updated_date":"2021-12-14 17:48:27.978","created_by":125,"version":1,"promotion_condition_id":392},{"condition_qty":2.000,"product_id":10,"updated_by":125,"promotion_scheme_id":130,"promotion_id":76,"created_date":"2021-12-14 17:52:00.354","updated_date":"2021-12-14 17:52:00.354","created_by":125,"version":1,"promotion_condition_id":393},{"condition_qty":5.000,"product_id":15,"updated_by":125,"promotion_scheme_id":131,"promotion_id":77,"created_date":"2021-12-14 17:53:48.714","updated_date":"2021-12-14 17:53:48.714","created_by":125,"version":1,"promotion_condition_id":394},{"condition_qty":2.000,"product_id":10,"updated_by":125,"promotion_scheme_id":132,"promotion_id":78,"created_date":"2021-12-14 18:00:31.425","updated_date":"2021-12-14 18:00:31.425","created_by":125,"version":1,"promotion_condition_id":395},{"condition_qty":2.000,"product_id":11,"updated_by":125,"promotion_scheme_id":132,"promotion_id":78,"created_date":"2021-12-14 18:00:31.425","updated_date":"2021-12-14 18:00:31.425","created_by":125,"version":1,"promotion_condition_id":396},{"condition_qty":2.000,"product_id":12,"updated_by":125,"promotion_scheme_id":132,"promotion_id":78,"created_date":"2021-12-14 18:00:31.425","updated_date":"2021-12-14 18:00:31.425","created_by":125,"version":1,"promotion_condition_id":397},{"condition_qty":2.000,"product_id":13,"updated_by":125,"promotion_scheme_id":132,"promotion_id":78,"created_date":"2021-12-14 18:00:31.425","updated_date":"2021-12-14 18:00:31.425","created_by":125,"version":1,"promotion_condition_id":398},{"condition_qty":3.000,"product_id":14,"updated_by":125,"promotion_scheme_id":133,"promotion_id":78,"created_date":"2021-12-14 18:00:31.441","updated_date":"2021-12-14 18:00:31.441","created_by":125,"version":1,"promotion_condition_id":399},{"condition_qty":3.000,"product_id":15,"updated_by":125,"promotion_scheme_id":133,"promotion_id":78,"created_date":"2021-12-14 18:00:31.441","updated_date":"2021-12-14 18:00:31.441","created_by":125,"version":1,"promotion_condition_id":400},{"condition_qty":2.000,"product_id":10,"updated_by":125,"promotion_scheme_id":134,"promotion_id":79,"created_date":"2021-12-14 18:01:38.800","updated_date":"2021-12-14 18:01:38.800","created_by":125,"version":1,"promotion_condition_id":401},{"condition_qty":2.000,"product_id":11,"updated_by":125,"promotion_scheme_id":134,"promotion_id":79,"created_date":"2021-12-14 18:01:38.800","updated_date":"2021-12-14 18:01:38.800","created_by":125,"version":1,"promotion_condition_id":402},{"condition_qty":2.000,"product_id":12,"updated_by":125,"promotion_scheme_id":134,"promotion_id":79,"created_date":"2021-12-14 18:01:38.800","updated_date":"2021-12-14 18:01:38.800","created_by":125,"version":1,"promotion_condition_id":403},{"condition_qty":2.000,"product_id":13,"updated_by":125,"promotion_scheme_id":134,"promotion_id":79,"created_date":"2021-12-14 18:01:38.800","updated_date":"2021-12-14 18:01:38.800","created_by":125,"version":1,"promotion_condition_id":404},{"condition_qty":3.000,"product_id":14,"updated_by":125,"promotion_scheme_id":135,"promotion_id":79,"created_date":"2021-12-14 18:01:38.816","updated_date":"2021-12-14 18:01:38.816","created_by":125,"version":1,"promotion_condition_id":405},{"condition_qty":3.000,"product_id":15,"updated_by":125,"promotion_scheme_id":135,"promotion_id":79,"created_date":"2021-12-14 18:01:38.816","updated_date":"2021-12-14 18:01:38.816","created_by":125,"version":1,"promotion_condition_id":406},{"condition_qty":2.000,"product_id":10,"updated_by":125,"promotion_scheme_id":136,"promotion_id":80,"created_date":"2021-12-14 18:04:57.239","updated_date":"2021-12-14 18:04:57.239","created_by":125,"version":1,"promotion_condition_id":407},{"condition_qty":2.000,"product_id":11,"updated_by":125,"promotion_scheme_id":136,"promotion_id":80,"created_date":"2021-12-14 18:04:57.239","updated_date":"2021-12-14 18:04:57.239","created_by":125,"version":1,"promotion_condition_id":408},{"condition_qty":2.000,"product_id":12,"updated_by":125,"promotion_scheme_id":136,"promotion_id":80,"created_date":"2021-12-14 18:04:57.239","updated_date":"2021-12-14 18:04:57.239","created_by":125,"version":1,"promotion_condition_id":409},{"condition_qty":2.000,"product_id":13,"updated_by":125,"promotion_scheme_id":136,"promotion_id":80,"created_date":"2021-12-14 18:04:57.255","updated_date":"2021-12-14 18:04:57.255","created_by":125,"version":1,"promotion_condition_id":410},{"condition_qty":3.000,"product_id":14,"updated_by":125,"promotion_scheme_id":137,"promotion_id":80,"created_date":"2021-12-14 18:04:57.255","updated_date":"2021-12-14 18:04:57.255","created_by":125,"version":1,"promotion_condition_id":411},{"condition_qty":3.000,"product_id":15,"updated_by":125,"promotion_scheme_id":137,"promotion_id":80,"created_date":"2021-12-14 18:04:57.255","updated_date":"2021-12-14 18:04:57.255","created_by":125,"version":1,"promotion_condition_id":412},{"condition_qty":7.000,"product_id":14,"updated_by":125,"promotion_scheme_id":140,"promotion_id":82,"created_date":"2022-01-08 18:37:56.336","updated_date":"2022-01-08 18:37:56.336","created_by":125,"version":1,"promotion_condition_id":419},{"condition_qty":7.000,"product_id":15,"updated_by":125,"promotion_scheme_id":140,"promotion_id":82,"created_date":"2022-01-08 18:37:56.336","updated_date":"2022-01-08 18:37:56.336","created_by":125,"version":1,"promotion_condition_id":420},{"condition_qty":5.000,"product_id":10,"updated_by":125,"promotion_scheme_id":141,"promotion_id":82,"created_date":"2022-01-08 18:37:56.352","updated_date":"2022-01-08 18:37:56.352","created_by":125,"version":1,"promotion_condition_id":421},{"condition_qty":5.000,"product_id":11,"updated_by":125,"promotion_scheme_id":141,"promotion_id":82,"created_date":"2022-01-08 18:37:56.352","updated_date":"2022-01-08 18:37:56.352","created_by":125,"version":1,"promotion_condition_id":422},{"condition_qty":5.000,"product_id":12,"updated_by":125,"promotion_scheme_id":141,"promotion_id":82,"created_date":"2022-01-08 18:37:56.352","updated_date":"2022-01-08 18:37:56.352","created_by":125,"version":1,"promotion_condition_id":423},{"condition_qty":5.000,"product_id":13,"updated_by":125,"promotion_scheme_id":141,"promotion_id":82,"created_date":"2022-01-08 18:37:56.368","updated_date":"2022-01-08 18:37:56.368","created_by":125,"version":1,"promotion_condition_id":424},{"condition_qty":1.000,"product_id":10,"updated_by":125,"promotion_scheme_id":214,"promotion_id":122,"created_date":"2022-01-18 10:22:17.880","updated_date":"2022-01-18 10:22:17.880","created_by":125,"version":1,"promotion_condition_id":651},{"condition_qty":1.000,"product_id":11,"updated_by":125,"promotion_scheme_id":214,"promotion_id":122,"created_date":"2022-01-18 10:22:17.880","updated_date":"2022-01-18 10:22:17.880","created_by":125,"version":1,"promotion_condition_id":652},{"condition_qty":1.000,"product_id":12,"updated_by":125,"promotion_scheme_id":214,"promotion_id":122,"created_date":"2022-01-18 10:22:17.880","updated_date":"2022-01-18 10:22:17.880","created_by":125,"version":1,"promotion_condition_id":653},{"condition_qty":1.000,"product_id":13,"updated_by":125,"promotion_scheme_id":214,"promotion_id":122,"created_date":"2022-01-18 10:22:17.880","updated_date":"2022-01-18 10:22:17.880","created_by":125,"version":1,"promotion_condition_id":654},{"condition_qty":1.000,"product_id":14,"updated_by":125,"promotion_scheme_id":214,"promotion_id":122,"created_date":"2022-01-18 10:22:17.895","updated_date":"2022-01-18 10:22:17.895","created_by":125,"version":1,"promotion_condition_id":655},{"condition_qty":1.000,"product_id":15,"updated_by":125,"promotion_scheme_id":214,"promotion_id":122,"created_date":"2022-01-18 10:22:17.895","updated_date":"2022-01-18 10:22:17.895","created_by":125,"version":1,"promotion_condition_id":656}]